{
  "source": {
    "file_name": "22062150-5818-40a7-a897-75e92001367e.docx",
    "file_path": "C:\\Users\\nchud\\Projects\\JobTrack\\data\\resume_in\\22062150-5818-40a7-a897-75e92001367e.docx",
    "extension": ".docx"
  },
  "profile": {
    "name": "",
    "email": "",
    "mobile_number": "",
    "designation": "",
    "total_experience": "",
    "education": ""
  },
  "skills": [],
  "company_names": [],
  "summary": {
    "ai_summary": "",
    "ai_strengths": []
  },
  "experiences": [],
  "user_email": "string"
}